README.md
setup.py
mgzdb/__init__.py
mgzdb/__main__.py
mgzdb/add.py
mgzdb/api.py
mgzdb/compress.py
mgzdb/extract.py
mgzdb/platforms.py
mgzdb/schema.py
mgzdb/util.py
mgzdb.egg-info/PKG-INFO
mgzdb.egg-info/SOURCES.txt
mgzdb.egg-info/dependency_links.txt
mgzdb.egg-info/entry_points.txt
mgzdb.egg-info/requires.txt
mgzdb.egg-info/top_level.txt