Metadata-Version: 1.1
Name: mgzdb
Version: 1.4.0
Summary: Age of Empires II recorded game database.
Home-page: https://github.com/siegeengineers/aoc-mgz-db/
Author: happyleaves
Author-email: happyleaves.tfr@gmail.com
License: MIT
Platform: UNKNOWN
Classifier: License :: OSI Approved :: MIT License
Classifier: Operating System :: OS Independent
Classifier: Programming Language :: Python :: 3
